aniketh/__init__.py
aniketh-0.0.1.dist-info/METADATA
aniketh-0.0.1.dist-info/WHEEL
aniketh-0.0.1.dist-info/top_level.txt
aniketh-0.0.1.dist-info/RECORD
